candidate.py
gpu_utils.py
pysigproc.py
pysigproc-0.4.0.data/scripts/h5plotter.py
pysigproc-0.4.0.dist-info/LICENSE
pysigproc-0.4.0.dist-info/METADATA
pysigproc-0.4.0.dist-info/WHEEL
pysigproc-0.4.0.dist-info/top_level.txt
pysigproc-0.4.0.dist-info/RECORD
